pyfi/__init__.py
pyfi/modul1.py
pyfi/modul2.py
etpyfitest1-0.0.8.dist-info/METADATA
etpyfitest1-0.0.8.dist-info/WHEEL
etpyfitest1-0.0.8.dist-info/top_level.txt
etpyfitest1-0.0.8.dist-info/RECORD
