Metadata-Version: 2.1
Name: etpyfitest1
Version: 0.0.8
Summary: Demonstrating how to use PyPI
Author: ExperTeach GmbH
Author-email: et_dbu@web.de
License: UNKNOWN
Keywords: python,code
Platform: UNKNOWN
Classifier: Development Status :: 1 - Planning
Classifier: Intended Audience :: Developers
Classifier: Programming Language :: Python :: 3
Classifier: Operating System :: Microsoft :: Windows
Requires-Dist: numpy
Requires-Dist: pandas
